[
    {
      "userId": 1,
      "userName": "Grażyna",
      "userSurname": "Krecik",
      "userAge": "31",
      "userGender": "kobieta",
      "userCity": "Radom",
      "userAvatar": "https://cdn1.iconfinder.com/data/icons/user-pictures/100/female1-512.png",
      "userDescription": "Szalona Graża mająca bzika na punkcie ogrodnictwa.",
      "userGardenImage": "https://encrypted-tbn0.gstatic.com/images?q=tbn:ANd9GcSi76RVKt2SvNrkFTEZY058vm6k25EwAq2StPzEOwKFl_97RXTBPg",
      "userDescriptionTitle": "Mój ogródek",
      "userGardenDescription": "Ogródek ze szklarnią i małym oczkiem wodnym o powierzchni pięćdziesięciu metrów kwadratowych. W planach stworzenie oczka wodnego."

    },
    {
        "userId": 2,
        "userName": "Stefan",
        "userSurname": "Ziółko",
        "userAge": "50",
        "userGender": "mężczyzna",
        "userCity": "Rzeszotary Panciawa",
        "userAvatar": "https://cdn1.iconfinder.com/data/icons/user-pictures/100/female1-512.png",
      "userDescription": "Szalona Graża mająca bzika na punkcie ogrodnictwa.",
      "userGardenImage": "https://encrypted-tbn0.gstatic.com/images?q=tbn:ANd9GcSi76RVKt2SvNrkFTEZY058vm6k25EwAq2StPzEOwKFl_97RXTBPg",
      "userDescriptionTitle": "Mój ogródek",
      "userGardenDescription": "Ogródek ze szklarnią i małym oczkiem wodnym o powierzchni pięćdziesięciu metrów kwadratowych. W planach stworzenie oczka wodnego."
      },
      {
        "userId": 3,
        "userName": "Jan",
        "userSurname": "Papryka",
        "userAge": "20",
        "userGender": "mężczyzna",
        "userCity": "Gdynia",
        "userAvatar": "https://cdn1.iconfinder.com/data/icons/user-pictures/100/female1-512.png",
      "userDescription": "Szalona Graża mająca bzika na punkcie ogrodnictwa.",
      "userGardenImage": "https://encrypted-tbn0.gstatic.com/images?q=tbn:ANd9GcSi76RVKt2SvNrkFTEZY058vm6k25EwAq2StPzEOwKFl_97RXTBPg",
      "userDescriptionTitle": "Mój ogródek",
      "userGardenDescription": "Ogródek ze szklarnią i małym oczkiem wodnym o powierzchni pięćdziesięciu metrów kwadratowych. W planach stworzenie oczka wodnego."
      },
      {
        "userId": 4,
        "userName": "Pamela",
        "userSurname": "Karmazyn",
        "userAge": "67",
        "userGender": "kobieta",
        "userCity": "Kielce"
      },
      {
        "userId": 5,
        "userName": "Melania",
        "userSurname": "Bila",
        "userAge": "37",
        "userGender": "kobieta",
        "userCity": "Warszawa"
      },

      {
        "userId": 6,
        "userName": "Karol",
        "userSurname": "Kretomróz",
        "userAge": "30",
        "userGender": "mężczyzna",
        "userCity": "Gdańsk"
      }
]